{
  "citations": [
    {
      "text": "Kultusministerkonferenz (2016/2017). Bildung in der digitalen Welt: Strategie der Kultusministerkonferenz. Beschluss vom 08.12.2016 i.d.F. vom 07.12.2017.",
      "url": "https://www.kmk.org/fileadmin/Dateien/veroeffentlichungen_beschluesse/2016/2016_12_08-Bildung-in-der-digitalen-Welt.pdf"
    }
  ],
  "humanCodingScheme": "5.4.2",
  "id": "OE-COMPETENCY-000972",
  "relations": {
    "skos:broader": [
      "OE-COMPETENCY-000970"
    ]
  },
  "statement": {
    "de": "Persönliches System von vernetzten digitalen Lernressourcen selbst organisieren können",
    "en": "Be able to organize a personal system of networked digital learning resources"
  },
  "status": "proposed",
  "type": "oe:Competency",
  "version": "1.0.0"
}
